<?xml version="1.0" encoding="UTF-8"?>
  <record xmlns="http://www.loc.gov/MARC21/slim" type="Authority">
    <leader>00000nz  a2200000nc 4500</leader>
    <controlfield tag="001">122497376</controlfield>
    <controlfield tag="003">DE-101</controlfield>
    <controlfield tag="005">20210217134842.0</controlfield>
    <controlfield tag="008">001114n||aznnnaabn           | aaa    |c</controlfield>
    <datafield tag="024" ind1="7" ind2=" ">
      <subfield code="a">122497376</subfield>
      <subfield code="0">http://d-nb.info/gnd/122497376</subfield>
      <subfield code="2">gnd</subfield>
    </datafield>
    <datafield tag="035" ind1=" " ind2=" ">
      <subfield code="a">(DE-101)122497376</subfield>
    </datafield>
    <datafield tag="035" ind1=" " ind2=" ">
      <subfield code="a">(DE-588)122497376</subfield>
    </datafield>
    <datafield tag="035" ind1=" " ind2=" ">
      <subfield code="z">(DE-588a)122497376</subfield>
      <subfield code="9">v:zg</subfield>
    </datafield>
    <datafield tag="040" ind1=" " ind2=" ">
      <subfield code="a">DE-12</subfield>
      <subfield code="c">DE-12</subfield>
      <subfield code="9">r:DE-12</subfield>
      <subfield code="b">ger</subfield>
      <subfield code="d">0017</subfield>
    </datafield>
    <datafield tag="042" ind1=" " ind2=" ">
      <subfield code="a">gnd1</subfield>
    </datafield>
    <datafield tag="043" ind1=" " ind2=" ">
      <subfield code="c">XA-DE</subfield>
    </datafield>
    <datafield tag="075" ind1=" " ind2=" ">
      <subfield code="b">p</subfield>
      <subfield code="2">gndgen</subfield>
    </datafield>
    <datafield tag="075" ind1=" " ind2=" ">
      <subfield code="b">piz</subfield>
      <subfield code="2">gndspec</subfield>
    </datafield>
    <datafield tag="079" ind1=" " ind2=" ">
      <subfield code="a">g</subfield>
      <subfield code="q">a</subfield>
      <subfield code="q">f</subfield>
    </datafield>
    <datafield tag="100" ind1="1" ind2=" ">
      <subfield code="a">Creidius, Johann Hartmann</subfield>
      <subfield code="d">1655-1709</subfield>
    </datafield>
    <datafield tag="400" ind1="1" ind2=" ">
      <subfield code="a">Creidius, Johannes Hartmann</subfield>
      <subfield code="d">1655-1709</subfield>
    </datafield>
    <datafield tag="400" ind1="1" ind2=" ">
      <subfield code="a">Creidius, Johannes Hartmannus</subfield>
      <subfield code="d">1655-1709</subfield>
    </datafield>
    <datafield tag="400" ind1="1" ind2=" ">
      <subfield code="a">Creidius, Joh. Hartmannus</subfield>
      <subfield code="d">1655-1709</subfield>
    </datafield>
    <datafield tag="400" ind1="1" ind2=" ">
      <subfield code="a">Creidt, Johann Hartmann</subfield>
      <subfield code="d">1655-1709</subfield>
    </datafield>
    <datafield tag="400" ind1="1" ind2=" ">
      <subfield code="a">Creidt, Johannes Hartmann</subfield>
      <subfield code="d">1655-1709</subfield>
    </datafield>
    <datafield tag="400" ind1="1" ind2=" ">
      <subfield code="a">Kreidt, Johann Hartmann</subfield>
      <subfield code="d">1655-1709</subfield>
    </datafield>
    <datafield tag="400" ind1="1" ind2=" ">
      <subfield code="a">Kreidt, Johannes Hartmann</subfield>
      <subfield code="d">1655-1709</subfield>
    </datafield>
    <datafield tag="400" ind1="1" ind2=" ">
      <subfield code="a">Creide, Johann Hartmann</subfield>
      <subfield code="d">1655-1709</subfield>
    </datafield>
    <datafield tag="548" ind1=" " ind2=" ">
      <subfield code="a">1655-1709</subfield>
      <subfield code="4">datl</subfield>
      <subfield code="4">https://d-nb.info/standards/elementset/gnd#dateOfBirthAndDeath</subfield>
      <subfield code="w">r</subfield>
      <subfield code="i">Lebensdaten</subfield>
      <subfield code="9">v:Todesdatum geschätzt</subfield>
    </datafield>
    <datafield tag="548" ind1=" " ind2=" ">
      <subfield code="a">1676-1709</subfield>
      <subfield code="4">datw</subfield>
      <subfield code="4">https://d-nb.info/standards/elementset/gnd#periodOfActivity</subfield>
      <subfield code="w">r</subfield>
      <subfield code="i">Wirkungsdaten</subfield>
    </datafield>
    <datafield tag="550" ind1=" " ind2=" ">
      <subfield code="0">(DE-101)041325923</subfield>
      <subfield code="0">(DE-588)4132592-8</subfield>
      <subfield code="0">https://d-nb.info/gnd/4132592-8</subfield>
      <subfield code="a">Pfarrer</subfield>
      <subfield code="4">berc</subfield>
      <subfield code="4">https://d-nb.info/standards/elementset/gnd#professionOrOccupation</subfield>
      <subfield code="w">r</subfield>
      <subfield code="i">Charakteristischer Beruf</subfield>
    </datafield>
    <datafield tag="551" ind1=" " ind2=" ">
      <subfield code="0">(DE-101)040036146</subfield>
      <subfield code="0">(DE-588)4003614-5</subfield>
      <subfield code="0">https://d-nb.info/gnd/4003614-5</subfield>
      <subfield code="a">Augsburg</subfield>
      <subfield code="4">ortg</subfield>
      <subfield code="4">https://d-nb.info/standards/elementset/gnd#placeOfBirth</subfield>
      <subfield code="w">r</subfield>
      <subfield code="i">Geburtsort</subfield>
    </datafield>
    <datafield tag="551" ind1=" " ind2=" ">
      <subfield code="0">(DE-101)04020989X</subfield>
      <subfield code="0">(DE-588)4020989-1</subfield>
      <subfield code="0">https://d-nb.info/gnd/4020989-1</subfield>
      <subfield code="a">Gießen</subfield>
      <subfield code="4">ortw</subfield>
      <subfield code="4">https://d-nb.info/standards/elementset/gnd#placeOfActivity</subfield>
      <subfield code="w">r</subfield>
      <subfield code="i">Wirkungsort</subfield>
    </datafield>
    <datafield tag="551" ind1=" " ind2=" ">
      <subfield code="0">(DE-101)040666409</subfield>
      <subfield code="0">(DE-588)4066640-2</subfield>
      <subfield code="0">https://d-nb.info/gnd/4066640-2</subfield>
      <subfield code="a">Wittenberg</subfield>
      <subfield code="4">ortw</subfield>
      <subfield code="4">https://d-nb.info/standards/elementset/gnd#placeOfActivity</subfield>
      <subfield code="w">r</subfield>
      <subfield code="i">Wirkungsort</subfield>
    </datafield>
    <datafield tag="551" ind1=" " ind2=" ">
      <subfield code="0">(DE-101)04057878X</subfield>
      <subfield code="0">(DE-588)4057878-1</subfield>
      <subfield code="0">https://d-nb.info/gnd/4057878-1</subfield>
      <subfield code="a">Straßburg</subfield>
      <subfield code="4">ortw</subfield>
      <subfield code="4">https://d-nb.info/standards/elementset/gnd#placeOfActivity</subfield>
      <subfield code="w">r</subfield>
      <subfield code="i">Wirkungsort</subfield>
    </datafield>
    <datafield tag="551" ind1=" " ind2=" ">
      <subfield code="0">(DE-101)957922787</subfield>
      <subfield code="0">(DE-588)4570211-1</subfield>
      <subfield code="0">https://d-nb.info/gnd/4570211-1</subfield>
      <subfield code="a">Põltsamaa</subfield>
      <subfield code="4">ortw</subfield>
      <subfield code="4">https://d-nb.info/standards/elementset/gnd#placeOfActivity</subfield>
      <subfield code="w">r</subfield>
      <subfield code="i">Wirkungsort</subfield>
    </datafield>
    <datafield tag="551" ind1=" " ind2=" ">
      <subfield code="0">(DE-101)944704441</subfield>
      <subfield code="0">(DE-588)4379454-3</subfield>
      <subfield code="0">https://d-nb.info/gnd/4379454-3</subfield>
      <subfield code="a">Kursi</subfield>
      <subfield code="g">Estland</subfield>
      <subfield code="4">ortw</subfield>
      <subfield code="4">https://d-nb.info/standards/elementset/gnd#placeOfActivity</subfield>
      <subfield code="w">r</subfield>
      <subfield code="i">Wirkungsort</subfield>
    </datafield>
    <datafield tag="551" ind1=" " ind2=" ">
      <subfield code="0">(DE-101)050932934</subfield>
      <subfield code="0">(DE-588)5093293-7</subfield>
      <subfield code="0">https://d-nb.info/gnd/5093293-7</subfield>
      <subfield code="a">Tallinn</subfield>
      <subfield code="4">orts</subfield>
      <subfield code="4">https://d-nb.info/standards/elementset/gnd#placeOfDeath</subfield>
      <subfield code="w">r</subfield>
      <subfield code="i">Sterbeort</subfield>
      <subfield code="9">v:Vermutlich in Tallinn 1709 gestorben.</subfield>
    </datafield>
    <datafield tag="667" ind1=" " ind2=" ">
      <subfield code="a">12</subfield>
    </datafield>
    <datafield tag="667" ind1=" " ind2=" ">
      <subfield code="a">VD-17</subfield>
    </datafield>
    <datafield tag="670" ind1=" " ind2=" ">
      <subfield code="a">Napiersky K.E., Beiträge zur Geschichte der Kirchen und Prediger in Livland, Bände 1-2, S. 42</subfield>
    </datafield>
    <datafield tag="670" ind1=" " ind2=" ">
      <subfield code="a">Misāns I., Riga und der Ostseeraum, S. 376</subfield>
    </datafield>
    <datafield tag="672" ind1=" " ind2="0">
      <subfield code="a">Petersen, Johann Wilhelm: Osculum legis naturae cum praecepto primo decalogi. - 1676</subfield>
    </datafield>
    <datafield tag="672" ind1=" " ind2="0">
      <subfield code="a">Creidius, Johann Hartmann: Augspurgisches Danck und Denckmahl. - 1709</subfield>
    </datafield>
    <datafield tag="672" ind1=" " ind2="0">
      <subfield code="a">Creidius, Johann Hartmann: Nothwendige Lebens-Pflichten, Welche wir in acht nehmen müssen ... - ca. 1709</subfield>
    </datafield>
    <datafield tag="678" ind1=" " ind2=" ">
      <subfield code="b">Evangelischer Pfarrer; Aus Augsburg; 1676 Defendent an der Univ. Gießen, Studium in Wittenberg, 1678 in Tübingen und Straßburg; nach dem Studium als Kandidat offenbar zeitweise in Frankfurt a. M.; ab 1692 Hauslehrer in Estland, einige Wochen Prediger in Maholm (Viru-Nigula). 1693 Diakon in Oberpahlen (Põltsamaa). Ab 1701 Pastor in Talkhof (Puurmani), Kirche Kursi, in Ostestland, 1705 an verschiedenen Kirchen als Seelsorger/Gnadenjahrsprediger, starb vermutlich 1709 in Tallinn.</subfield>
    </datafield>
    <datafield tag="913" ind1=" " ind2=" ">
      <subfield code="S">pnd</subfield>
      <subfield code="i">a</subfield>
      <subfield code="a">Creidius, Johann Hartmann</subfield>
      <subfield code="0">(DE-588a)122497376</subfield>
    </datafield>
  </record>
